palgoviz/__init__.py
palgoviz/adders.py
palgoviz/bobcats.py
palgoviz/caching.py
palgoviz/calc.py
palgoviz/compare.py
palgoviz/composers.py
palgoviz/context.py
palgoviz/datarace.py
palgoviz/dechello.py
palgoviz/decnotes.py
palgoviz/decorators.py
palgoviz/enumerations.py
palgoviz/fib.py
palgoviz/fibonacci.py
palgoviz/fizzbuzz.py
palgoviz/fizzbuzz69.py
palgoviz/fizzbuzz_mc.py
palgoviz/functions.py
palgoviz/gencomp1.py
palgoviz/gencomp2.py
palgoviz/greet.py
palgoviz/greetall.py
palgoviz/hola.py
palgoviz/iterators.py
palgoviz/match_demo.py
palgoviz/object_graph.py
palgoviz/queues.py
palgoviz/recursion.py
palgoviz/scopes.py
palgoviz/simple.py
palgoviz/sll.py
palgoviz/strings.py
palgoviz/subproblems_wip.py
palgoviz/testing.py
palgoviz/util.py
palgoviz-0.1.0.dist-info/LICENSE
palgoviz-0.1.0.dist-info/METADATA
palgoviz-0.1.0.dist-info/WHEEL
palgoviz-0.1.0.dist-info/RECORD
