Metadata-Version: 2.1
Name: palgoviz
Version: 0.1.0
Summary: Materials for Python and algorithms, with visualization
Home-page: https://github.com/EliahKagan/palgoviz
License: 0BSD
Keywords: algorithms,teaching,visualization
Author: David Vassallo
Author-email: vassallo.davidm@gmail.com
Maintainer: Eliah Kagan
Maintainer-email: degeneracypressure@gmail.com
Requires-Python: >=3.11,<3.12
Classifier: Development Status :: 3 - Alpha
Classifier: Framework :: Jupyter :: JupyterLab
Classifier: Framework :: Jupyter :: JupyterLab :: 3
Classifier: Intended Audience :: Developers
Classifier: Intended Audience :: Education
Classifier: License :: OSI Approved
Classifier: License :: Other/Proprietary License
Classifier: Programming Language :: Python :: 3
Classifier: Programming Language :: Python :: 3.11
Classifier: Topic :: Scientific/Engineering :: Visualization
Requires-Dist: graphviz (>=0.20.1,<0.21.0)
Requires-Dist: more-itertools (>=9.0.0,<10.0.0)
Requires-Dist: sympy (>=1.11.1,<2.0.0)
Project-URL: Repository, https://github.com/EliahKagan/palgoviz
